[{"file": "quals_2/m-bong-henry-chua-yang.json", "scores": [["Bong Kok Wei", 380], ["Chua Wang Zhi", 220], ["Yang Chen", 150], ["Henry Jefferson Co Morco", 60]]}, {"file": "quals_2/m-ang-katherine-cheong-ng.json", "scores": [["Cheong Yu Jia", 690], ["Ang Chern-Mao Kegan", 610], ["Katherine Anne Narag Catapang", 190], ["Ng Say-Yao Mark", 40]]}, {"file": "quals_2/m-wu-low-imaduddin-tan.json", "scores": [["Tan Chee Peng", 360], ["Imaduddin Haetami", 290], ["Wu Yu Ting", 240], ["Low Zi Xin", 140]]}, {"file": "quals_2/m-laura-chng-teo-toh-leon.json", "scores": [["Teo Meng How", 580], ["Chng Ming Shin", 390], ["Toh Qi Hui", 190], ["Laura Tan", 90], ["Leon Poh", 50]]}, {"file": "quals_2/m-toh-rowena-nguyen-lee-angie.json", "scores": [["Nguyen Tu Anh", 960], ["Rowena Yap Kah Sin", 640], ["Lee Yong Sheng", 150], ["Toh Hongyi", 130], ["Angie Ho", 20]]}]